abstractions/__init__.py
abstractions/abs_exceptions.py
abstractions/augmentation.py
abstractions/base_class.py
abstractions/data_loading.py
abstractions/eval_utils.py
abstractions/evaluate.py
abstractions/evaluation.py
abstractions/model_building.py
abstractions/orchestration.py
abstractions/preprocessing.py
abstractions/submit_training_job.py
abstractions/train.py
abstractions/training.py
abstractions/utils.py
abstractions/tests/__init__.py
abstractions/tests/test_components.py
abstractions/tests/test_initialization.py
abstractions_aimedic-0.1.15.dist-info/LICENSE.txt
abstractions_aimedic-0.1.15.dist-info/METADATA
abstractions_aimedic-0.1.15.dist-info/WHEEL
abstractions_aimedic-0.1.15.dist-info/entry_points.txt
abstractions_aimedic-0.1.15.dist-info/top_level.txt
abstractions_aimedic-0.1.15.dist-info/RECORD
